{
    "url": "https://www.neptun.mk/categories/PERSONALNI_KOMPJUTERI/DELL-PC-OptiPlex-7410-23-8--i5-13500T-8GB-256GB-KB-Mouse",
    "title": "AIO DELL PC OPTIPLEX 7410 23.8\" I5-13500T/8GB/256GB/KB+MOUSE",
    "warranty": "24",
    "regular_price": "54.999",
    "happy_price": "48.999",
    "description": [
        "Дисплеј:23.8\"(60.45cm)\nРезолуција:(1920x1080)FHD, Integrated Graphics, WVA Touch Anti-Glare, HDMI, FHD Camera\nПроцесор: 13th Gen Intel® Core™ i5-13500 (24 MB cache, 14 cores, 20 threads, 2.50 GHz to 4.80 GHz Turbo, 65 W)\nГрафика: Intel® Graphics\nRAM Меморија: 8 GB DDR4\nДиск (Storage): 256 GB, M.2 2230, PCIe NVMe, SSD, Class 35\nWi-Fi-6E 2x2 AX211 Bluetooth 5.2 Wireless Card\nDell Pro Wireless Keyboard and Mouse - KM5221W Black - US English\nКамера: FHD camera\nБез оперативен систем\nПорти:\n1 USB 3.2 Gen 2x2 Type-C port\n1 HDMI-out 1.4/HDCP 2.3 port, up to 4096 x 2160 @ 60Hz\n1 HDMI-in 2.1/HDCP 1.4 port, up to 1920 x 1080 @ 60Hz\n1 DisplayPort 1.4a/HDCP 2.3 port, up to 5120 x 3200 @ 60Hz\n1 RJ45 Ethernet Port 10/100/1000 Mbps port\n2 USB 3.2 Gen 1 Type-A ports with Smart Power On\n2 USB 3.2 Gen 2 Type-A ports\n1 Audio line-out port\n1 USB 3.2 Gen 2 Type-A port with PowerShare\n1 Universal audio port\nНапојување: 130 W AC adapter"
    ],
    "category": "PERSONALNI_KOMPJUTERI"
}