{
    "url": "https://www.neptun.mk/categories/SOUNDBAR/SAMSUNG-HW-Q990D-EN",
    "title": "SAMSUNG HW-Q990D/EN",
    "warranty": "24",
    "regular_price": "87.999",
    "happy_price": "",
    "description": [
        "Soundbar\nБезжичен Dolby Atmos / DTS:X\nВистински 11.1.4 звук\nQ-Symphony\nSpaceFit Sound Pro\nБрој на звучници: 22\nЗвучници:\nЦентрален звучник\nЗвучник насочен нагоре\nFront Wide-firing Speaker\nСтранични звучници\nWireless Subwoofer Included\nВклучен безжичен заден звучник\nActive Voice Amplifier\nSpaceFit Sound\nРежим на звук:\nSurround Sound expansion\nGame Pro\nStandard\nAdaptive\nHDR 10+\nПоврзување:\nHDMI влез x2\nHDMI излез x1\nHDMI ARC\nOptical In\nBluetooth v5.2\nWi-Fi\nOne Remote Control\nSmartThings App\nMulti Position Rear Speaker\nChromecast\nSpotify Connect\nAirPlay\nWireless Dolby ATMOS\nAlexa"
    ],
    "category": "SOUNDBAR"
}