{
    "url": "https://www.neptun.mk/categories/prenosni_kompjuteri/MacBook-Pro-14-M3-8C-CPU-10C-GPU-8GB-512GB-Space-Grey-mtl73ze-a",
    "title": "APPLE MACBOOK PRO 14 M3/8C CPU/10C GPU/8GB/512GB SPACE GREY",
    "warranty_months": 12,
    "regular_price_mkd": 120999,
    "happy_price_mkd": 117999,
    "category": "prenosni_kompjuteri",
    "device_type": "Laptop",
    "description": "\u041b\u0430\u043f\u0442\u043e\u043f\n\u0414\u0438\u0441\u043f\u043b\u0435\u0458:14.2\"(36cm) Liquid Retina XDR display\n\u041f\u0440\u043e\u0446\u0435\u0441\u043e\u0440:Apple M3 8?core CPU, 10?core GPU\n\u0413\u0440\u0430\u0444\u0438\u043a\u0430: 10?core GPU\nRAM \u043c\u0435\u043c\u043e\u0440\u0438\u0458\u0430:8GB\n\u0414\u0438\u0441\u043a (Storage): 512GB SSD\n1080p FaceTime HD camera\n\u0422\u0440\u0438 \u043c\u0438\u043a\u0440\u043e\u0444\u043e\u043d\u0438\nBacklit Magic Keyboard \u0441\u043e Touch ID\nBluetooth 5.3\nWireless: Wi-Fi 6E\nSDXC card slot\nHDMI port\n3.5 mm headphone jack\nMagSafe 3 port\n\u0422\u0440\u0438 Thunderbolt 4 (USB-C) ports",
    "features": {
        "screen_size_inches": 14.2,
        "screen_resolution": null,
        "screen_refresh_rate_hz": null,
        "screen_brightness_nits": null,
        "screen_type": "Liquid Retina XDR",
        "processor_model": "Apple M3",
        "processor_cores": 8,
        "processor_threads": null,
        "processor_base_clock_ghz": null,
        "processor_max_clock_ghz": null,
        "gpu_model": "10-core",
        "gpu_memory_gb": null,
        "ram_size_gb": 8,
        "ram_type": null,
        "storage_size_gb": 512,
        "storage_type": "SSD",
        "operating_system": null,
        "wifi_standard": "Wi-Fi 6E",
        "bluetooth_version": 5.3,
        "usb_type_c_ports": 3,
        "usb_type_a_ports": null,
        "hdmi_ports": 1,
        "audio_jack_ports": 1,
        "card_reader": "SDXC",
        "keyboard_type": "Backlit Magic Keyboard",
        "audio_feature_1": null,
        "battery_capacity_wh": null,
        "battery_cells": null,
        "security_feature_1": "Touch ID"
    }
}