{
    "url": "https://www.neptun.mk/categories/prenosni_kompjuteri/Apple-MacBook-Air-13-6-M3-8C-CPU-10C-GPU-8GB-512GB-Midnight-mrxw3ze-a",
    "title": "",
    "warranty": "12",
    "regular_price": "93.399",
    "happy_price": "",
    "description": [
        "Лаптоп\nДисплеј:13.6\"(34.5cm)\nПроцесор:Apple M3 chip with 8-core\nGPU 10?core\nРезолуција:(2560x1664) Liquid Retina display, 224ppi, 500nits\nМеморија:8GB\n512GB SSD\nFaceTime HD камера од 1080p\nТри микрофони\nСистем од четири звучници со Spatial audio.\nBacklit Magic Keyboard со Touch ID, Ambient light sensor\nForce Touch Trackpad\nBluetooth 5.3\nWi?Fi 6E (802.11ax)\n2 x Thunderbolt / USB 4\nMagSafe 3 charging port\n3.5 mm headphone jack\nCharging\nDisplayPort\nThunderbolt 3 (up to 40Gb/s)\nUSB 4 (up to 40Gb/s)\nUSB 3.1 Gen 2 (up to 10Gb/s)\n30W USB-C Power Adapter\nБатерија:52,6 Wh - 18 h"
    ],
    "category": "prenosni_kompjuteri"
}