{
    "url": "https://www.neptun.mk/categories/prenosni_kompjuteri/LENOVO-IdeaPad-Slim-3-15IAH8-i5-12450H-16GB-DDR5-512GB",
    "title": "ЛАПТОП LENOVO IDEAPAD SLIM 3 15IAH8 I5-12450H/16GB DDR5/512GB",
    "warranty": "24",
    "regular_price": "31.999",
    "happy_price": "28.999",
    "description": [
        "Лаптоп\nДисплеј:15.6\" (39.6cm)\nРезолуција:(1920x1080) FHD, TN 250nits Anti-glare\nЧипсет: Intel® SoC Platform\nПроцесор: Intel® Core™ i5-12450H, 8C (4P + 4E) / 12T, P-core 2.0 / 4.4GHz, E-core 1.5 / 3.3GHz, 12MB\nГрафика:Integrated Intel® UHD Graphics\nRAM Меморија: 16GB Soldered LPDDR5-4800\nДиск (Storage): 512GB SSD M.2 2242 PCIe® 4.0x4 NVMe®\nWLAN + Bluetooth: 11ac 2x2 + BT5.1\nПорти:\n2x USB 3.2 Gen 1\n1x USB-C® 3.2 Gen 1 (support data transfer, Power Delivery and DisplayPort™ 1.2)\n1x HDMI® 1.4\n1x Card reader\n1x Headphone / microphone combo jack (3.5mm)\n1x Power connector\nБез оперативен систем\nАудио:High Definition (HD) Audio\nЗвучник:Stereo speakers, 1.5W x2, Dolby® Audio™\nКамера: HD 720p with Privacy Shutter\nPower Adapter - 65W Round Tip (3-pin)\nБатерија:47Wh"
    ],
    "category": "prenosni_kompjuteri"
}