{
    "url": "https://www.neptun.mk/categories/KABLI_I_RAZDELNICI/SUKO-SAS---2usb-2,1a-polnac-za-mobilni-bel",
    "title": "SUKO SAS + 2USB 2,1A POLNAC ZA MOBILNI BEL",
    "warranty_months": 72,
    "regular_price_mkd": 799,
    "happy_price_mkd": 547,
    "category": "KABLI_I_RAZDELNICI",
    "description": "\u0428\u0443\u043a\u043e SAS + 2USB 2.1\u0410 \u043f\u043e\u043b\u043d\u0430\u0447 \u0437\u0430 \u043c\u043e\u0431\u0438\u043b\u043d\u0438 \u0431\u0435\u043b",
    "features": {
        "device_type": "Cable or Divider"
    }
}