{
    "url": "https://www.neptun.mk/categories/KABLI_I_RAZDELNICI/SAS-2-suko---2-prekin--Bel",
    "title": "\u0420\u0410\u0417\u0414\u0415\u041b\u041d\u0418\u041a SAS 2 SUKO + 2 \u041f\u0420\u0415\u041a\u0418\u041d. BEL",
    "warranty_months": 72,
    "regular_price_mkd": 399,
    "happy_price_mkd": null,
    "category": "KABLI_I_RAZDELNICI",
    "description": "\u0420\u0410\u0417\u0414\u0415\u041b\u041d\u0418\u041a SAS 2 SUKO + 2 \u041f\u0420\u0415\u041a\u0418\u041d. BEL",
    "features": {
        "device_type": "Divider",
        "number_of_sockets": 2,
        "max_power_watts": null,
        "voltage_volts": null,
        "cable_length_meters": null,
        "input_type": null,
        "output_type": null,
        "resolution_supported": null
    }
}