{
    "url": "https://www.neptun.mk/categories/mobilni_telefoni/HONOR-X7b-6-128GB-Midnight-Black--Clark-L31B1-",
    "title": "HONOR X7B, 6.8\", 108MP+5MP+2MP/8MP, 6/128GB, 5330MAH, MIDNIGHT BLACK (CLARK-L31B1)",
    "warranty": "24",
    "regular_price": "11.999",
    "happy_price": "9.999",
    "description": [
        "Мобилен телефон\nAndroid 13, MagicOS 7.2\nЕкран: 6.8\" (1080x2412) IPS LCD, 90Hz, 850 nits (peak)\nQualcomm SM6225 Snapdragon 680 4G (6 nm)\nOcta-core (4x2.4 GHz Kryo 265 Gold & 4x1.9 GHz Kryo 265 Silver)\nГрафика: Adreno 610\nИнтерна меморија:\nROM Меморија:128GB\nRAM Меморија:6GB\nПримарна камера:\n108 MP, f/1.8, 24mm (wide), 1/1.67\", 0.64µm, PDAF\n5 MP, f/2.2, (ultrawide)\n2 MP, f/2.4, (depth)\nСекундарна камера:\n8 MP, f/2.0, (wide)\nWi-Fi 802.11 a/b/g/n/ac, dual-band, Wi-Fi Direct\nBluetooth: 5.0, A2DP, LE\nGPS, GLONASS, GALILEO, BDS\nUSB Type-C 2.0, OTG\nБатерија: Li-Po 5330mAh\nПолнење: 35W wired"
    ],
    "category": "mobilni_telefoni"
}