{
    "url": "https://www.neptun.mk/categories/SOUNDBAR/SAMSUNG-HW-Q800C",
    "title": "SOUNDBAR SAMSUNG HW-Q800C, 360W",
    "warranty_months": 24,
    "regular_price_mkd": 39799,
    "happy_price_mkd": 27999,
    "category": "SOUNDBAR",
    "device_type": "Soundbar",
    "description": "Soundbar\n\u041c\u043e\u045c\u043d\u043e\u0441\u0442:360 W\n5.1.2 chanel\n\u0411\u0440\u043e\u0458 \u043d\u0430 \u0437\u0432\u0443\u0447\u043d\u0438\u0446\u0438: 11\n3D \u043e\u043f\u043a\u0440\u0443\u0436\u0443\u0432\u0430\u0447\u043a\u0438 \u0437\u0432\u0443\u043a \u0441\u043e \u0431\u0435\u0437\u0436\u0438\u0447\u0435\u043d Dolby Atmos \u0438 DTS:X\nQ-Symphony\n\u041e\u043f\u0442\u0438\u043c\u0438\u0437\u0430\u0446\u0438\u0458\u0430 \u043d\u0430 \u0437\u0432\u0443\u043a\u043e\u0442 \u0441\u043e SpaceFit Sound Pro\nHDR 10+\nWi-Fi\nBluetooth\n\u041a\u043e\u043d\u0435\u043a\u0446\u0438\u0458\u0430:\nHDMI, HDMI ARC\nSmartThings \u0430\u043f\u043b\u0438\u043a\u0430\u0446\u0438\u0458\u0430\nAirPlay2\nSpotify Connect",
    "features": {
        "number_of_channels": "5.1.2",
        "number_of_speakers": 11,
        "audio_3d_support": true,
        "audio_3d_technologies": [
            "Dolby Atmos",
            "DTS:X"
        ],
        "q_symphony": true,
        "spacefit_sound_pro": true,
        "hdr_support": true,
        "hdr_formats": [
            "HDR 10+"
        ],
        "wireless_connectivity": true,
        "wireless_technologies": [
            "Wi-Fi",
            "Bluetooth"
        ],
        "connections": [
            "HDMI",
            "HDMI ARC"
        ],
        "smart_home_compatibility": "SmartThings",
        "smart_audio_ecosystem": "AirPlay2",
        "music_streaming_services": [
            "Spotify Connect"
        ]
    }
}