{
    "url": "https://www.neptun.mk/categories/televizori/PHILIPS-75-PML-9008",
    "title": "PHILIPS 75 PML 9008",
    "warranty": "24",
    "regular_price": "79.999",
    "happy_price": "",
    "description": [
        "75\"(189cm) MINI LED 4K Ambilight TV\nРезолуција:3.840 x 2.160\nP5 Perfect Picture Engine\nSmart TV with improved OS\nСтапка на освежување:  120Hz\nHDR+\nAmbilight 3-sided - позадинско осветлување\nAmbilight Music\nAmbiWakeup\nAmbiSleep\nAmbilight Boot-Up Animation\nGame Mode\nMicro Dimming Premium\nDolby Vision\nDolby Atmos\nPerfect Natural Motion\nКонекција:\n4 x HDMI, 2 x USB, LAN RJ-45, CI+\n1 x Digital audio out (optical)\n1 x Headphone out\nDVB-T/T2/T2-HD/C/S/S2\nВграден Wifi"
    ],
    "category": "televizori"
}