{
    "url": "https://www.neptun.mk/categories/televizori/SAMSUNG-UE-85-CU-7172-UXXH",
    "title": "4К UHD SMART TV SAMSUNG UE 85 CU 7172 UXXH 85\" (215.9CM)",
    "warranty": "24",
    "regular_price": "121.999",
    "happy_price": "87.999",
    "description": [
        "85\" (215.9cm) 4К UHD Smart TV\nРезолуција:3.840 x 2.160\nOperating System Tizen™\nCrystal Processor 4K\nPurColor\nМега контраст\nHDR 10+\nUHD Dimming\nObject Tracking Sound Lite (OTS Lite)\nQ-Symphony\nИзлез за звук (RMS): 20W\nАдаптивен звук\n2CH audio\nAuto Game Mode (ALLM)\nMotion Xcelerator\n3xHDMI,1xUSB,eARC,LAN, CI\nBluetooth 5.2\nSmartThings\nMedia Home\nDVB-T2/C/S2\nВграден Wi-Fi"
    ],
    "category": "televizori"
}